MANIFEST.in
README.md
flask_scaffold.py
setup.cfg
setup.py
structure.yml
Flask_Mongo_Scaffold.egg-info/PKG-INFO
Flask_Mongo_Scaffold.egg-info/SOURCES.txt
Flask_Mongo_Scaffold.egg-info/dependency_links.txt
Flask_Mongo_Scaffold.egg-info/entry_points.txt
Flask_Mongo_Scaffold.egg-info/requires.txt
Flask_Mongo_Scaffold.egg-info/top_level.txt
stubs/__init__.py.jinja2
stubs/api.views.py.jinja2
stubs/base.html.jinja2
stubs/config.py.jinja2
stubs/index.html.jinja2
stubs/instance.config.py.jinja2
stubs/models.py.jinja2
stubs/requirements.txt.jinja2
stubs/run.py.jinja2
stubs/web.views.py.jinja2