Metadata-Version: 2.1
Name: Flask-Mongo-Scaffold
Version: 0.1
Summary: A tool to generate a simple flask app using MongoDB
Home-page: https://github.com/richin13/flask-scaffold
Author: Ricardo Madriz
License: UNKNOWN
Project-URL: Bug Reports, https://github.com/richin13/flask-scaffold/issues
Project-URL: Source, https://github.com/richin13/flask-scaffold/issues
Keywords: flask scaffold mongodb development
Platform: UNKNOWN
Classifier: Development Status :: 3 - Alpha
Classifier: Environment :: Console
Classifier: Framework :: Flask
Classifier: Intended Audience :: Developers
Classifier: License :: OSI Approved :: MIT License
Classifier: Operating System :: Unix
Classifier: Programming Language :: Python :: 3
Classifier: Programming Language :: Python :: 3.4
Classifier: Programming Language :: Python :: 3.5
Classifier: Programming Language :: Python :: 3.6
Classifier: Topic :: Software Development :: Code Generators
Classifier: Topic :: Utilities
